miniagents/__init__.py
miniagents/ext/__init__.py
miniagents/ext/agents/__init__.py
miniagents/ext/agents/aggregator_agents.py
miniagents/ext/agents/history_agents.py
miniagents/ext/agents/misc_agents.py
miniagents/ext/integrations/__init__.py
miniagents/ext/integrations/llama_index.py
miniagents/ext/llms/__init__.py
miniagents/ext/llms/anthropic.py
miniagents/ext/llms/llm_utils.py
miniagents/ext/llms/openai.py
miniagents/messages.py
miniagents/miniagent_typing.py
miniagents/miniagents.py
miniagents/promising/__init__.py
miniagents/promising/errors.py
miniagents/promising/ext/__init__.py
miniagents/promising/ext/frozen.py
miniagents/promising/promise_typing.py
miniagents/promising/promising.py
miniagents/promising/sentinels.py
miniagents/promising/sequence.py
miniagents/utils.py
miniagents-0.0.34.dist-info/LICENSE
miniagents-0.0.34.dist-info/METADATA
miniagents-0.0.34.dist-info/WHEEL
miniagents-0.0.34.dist-info/RECORD
