Metadata-Version: 2.1
Name: miniagents
Version: 0.0.34
Summary: An open-source, async-first framework for building multi-agent AI systems with an innovative approach to parallelism, so you can focus on creating intelligent agents, not on managing the concurrency of your flows.
Home-page: https://github.com/teremterem/MiniAgents
License: MIT
Author: Oleksandr Tereshchenko
Author-email: toporok@gmail.com
Requires-Python: >=3.9,<4.0
Classifier: License :: OSI Approved :: MIT License
Classifier: Programming Language :: Python :: 3
Classifier: Programming Language :: Python :: 3.9
Classifier: Programming Language :: Python :: 3.10
Classifier: Programming Language :: Python :: 3.11
Classifier: Programming Language :: Python :: 3.12
Requires-Dist: markdown-it-py
Requires-Dist: prompt-toolkit
Requires-Dist: pydantic (>=2.0.0,<3.0.0)
Requires-Dist: wrapt
